deesom/__init__.py
deesom/deesom.py
sompy/__init__.py
sompy/codebook.py
sompy/decorators.py
sompy/neighborhood.py
sompy/normalization.py
sompy/sompy.py
sompy/visualization/__init__.py
sompy/visualization/bmuhits.py
sompy/visualization/dotmap.py
sompy/visualization/histogram.py
sompy/visualization/hitmap.py
sompy/visualization/mapview.py
sompy/visualization/umatrix.py
sompy/visualization/view.py
deeSOM-1.0.dist-info/LICENSE
deeSOM-1.0.dist-info/METADATA
deeSOM-1.0.dist-info/WHEEL
deeSOM-1.0.dist-info/top_level.txt
deeSOM-1.0.dist-info/RECORD
