Metadata-Version: 2.1
Name: deeSOM
Version: 1.0
Summary: Deep ensemble-elastic self-organized map (deesom): a SOM based classifier to deal with large and highly imbalanced data.
Home-page: https://github.com/lbugnon/deesom
Author: lbugnon
Author-email: lbugnon@sinc.unl.edu.ar
License: UNKNOWN
Download-URL: https://github.com/lbugnon/deeSOM/archive/1.0.tar.gz
Platform: UNKNOWN
Classifier: Programming Language :: Python :: 3
Classifier: License :: OSI Approved :: MIT License
Classifier: Operating System :: OS Independent
Requires-Python: >=3.6
